Workbook

Sheet Precios
A1: Precio por millón de tokens (USD) · API de Anthropic · celdas azules editables
A3: Tipo de token | B3: Opus 5.5 | C3: Sonnet 5.5 | D3: Qué es
A4: Lectura de caché | B4: 0.2 | C4: 0.2 | D4: Contexto que ya estaba (tablero, skills, conversación) y se vuelve a leer en cada paso
A5: Escritura de caché (1 hora) | B5: 8 | C5: 4 | D5: Contexto nuevo que entra por primera vez: datos, resultados de scripts, capturas
A6: Salida | B6: 20 | C6: 10 | D6: Lo que escribe Claude: código del tablero, textos, insights
A7: Entrada sin caché | B7: 4 | C7: 2 | D7: Marginal en este tipo de trabajo
A10: Factor actualización (vs. primera vez) | B10: 0.45
A11: Tipo de cambio ARS por USD (opcional) | B11: 1
A13: Margen de precio sugerido (multiplicador sobre el costo de API) | B13: 2.5
A14: Margen de precio sugerido 2 (escenario conservador) | B14: 4

Sheet Cuadro
A1: Tokens y costo por canal y tamaño de base · Grande = escala real PAVIR/DRAKON (sesiones separadas por canal) · ±30%
A2: Chica/Mediana ancladas a lo medido (TKVA, BETROX, EDFAN). Grande es ~2x la Mediana real, consistente con que PAVIR/DRAKON (un tablero grande armado en una sola sesión) salió USD 32-50: armar cada canal en sesiones separadas cuesta más por no compartir caché entre canales.
A3: Canal | B3: Tamaño | C3: Qué significa el tamaño | D3: Pasos (llamadas) | E3: Contexto medio por paso (miles) | F3: Contexto nuevo escrito (miles) | G3: Salida (miles) | H3: Tokens · alta (cliente o canal nuevo, una sola vez) | I3: USD Opus · alta (una sola vez) | J3: Tokens · actualización con export nuevo (estructura ya hecha) | K3: USD Opus · actualización (cada export) | L3: USD Sonnet · actualización (cada export) | M3: ARS Opus · actualización | N3: Precio sugerido · alta (2,5x) | O3: Precio sugerido · actualización (2,5x) | P3: Precio sugerido · actualización (4x, conservador)
A4: Prometheo (CRM) | B4: Chica | C4: hasta 300 contactos, ~25 columnas | D4: 35 | E4: 110 | F4: 776 | G4: 63 | H4: =(D4*E4+F4+G4)*1000 | I4: =(D4*E4*Precios!$B$4+F4*Precios!$B$5+G4*Precios!$B$6)/1000 | J4: =H4*Precios!$B$10 | K4: =I4*Precios!$B$10 | L4: =(D4*E4*Precios!$C$4+F4*Precios!$C$5+G4*Precios!$C$6)/1000*Precios!$B$10 | M4: =K4*Precios!$B$11 | N4: =I4*Precios!$B$13 | O4: =K4*Precios!$B$13 | P4: =K4*Precios!$B$14
A5: Prometheo (CRM) | B5: Mediana | C5: ~1.000 contactos, ~40 columnas (BETROX, EDFAN) | D5: 61 | E5: 136 | F5: 1395 | G5: 124 | H5: =(D5*E5+F5+G5)*1000 | I5: =(D5*E5*Precios!$B$4+F5*Precios!$B$5+G5*Precios!$B$6)/1000 | J5: =H5*Precios!$B$10 | K5: =I5*Precios!$B$10 | L5: =(D5*E5*Precios!$C$4+F5*Precios!$C$5+G5*Precios!$C$6)/1000*Precios!$B$10 | M5: =K5*Precios!$B$11 | N5: =I5*Precios!$B$13 | O5: =K5*Precios!$B$13 | P5: =K5*Precios!$B$14
A6: Prometheo (CRM) | B6: Grande | C6: 5.000+ contactos, 50+ columnas, varios embudos | D6: 88 | E6: 172 | F6: 3033 | G6: 270 | H6: =(D6*E6+F6+G6)*1000 | I6: =(D6*E6*Precios!$B$4+F6*Precios!$B$5+G6*Precios!$B$6)/1000 | J6: =H6*Precios!$B$10 | K6: =I6*Precios!$B$10 | L6: =(D6*E6*Precios!$C$4+F6*Precios!$C$5+G6*Precios!$C$6)/1000*Precios!$B$10 | M6: =K6*Precios!$B$11 | N6: =I6*Precios!$B$13 | O6: =K6*Precios!$B$13 | P6: =K6*Precios!$B$14
A7: Meta Ads | B7: Chica | C7: hasta 10 anuncios, 1 mes | D7: 25 | E7: 100 | F7: 569 | G7: 46 | H7: =(D7*E7+F7+G7)*1000 | I7: =(D7*E7*Precios!$B$4+F7*Precios!$B$5+G7*Precios!$B$6)/1000 | J7: =H7*Precios!$B$10 | K7: =I7*Precios!$B$10 | L7: =(D7*E7*Precios!$C$4+F7*Precios!$C$5+G7*Precios!$C$6)/1000*Precios!$B$10 | M7: =K7*Precios!$B$11 | N7: =I7*Precios!$B$13 | O7: =K7*Precios!$B$13 | P7: =K7*Precios!$B$14
A8: Meta Ads | B8: Mediana | C8: ~30 anuncios, 3 meses | D8: 35 | E8: 116 | F8: 976 | G8: 85 | H8: =(D8*E8+F8+G8)*1000 | I8: =(D8*E8*Precios!$B$4+F8*Precios!$B$5+G8*Precios!$B$6)/1000 | J8: =H8*Precios!$B$10 | K8: =I8*Precios!$B$10 | L8: =(D8*E8*Precios!$C$4+F8*Precios!$C$5+G8*Precios!$C$6)/1000*Precios!$B$10 | M8: =K8*Precios!$B$11 | N8: =I8*Precios!$B$13 | O8: =K8*Precios!$B$13 | P8: =K8*Precios!$B$14
A9: Meta Ads | B9: Grande | C9: 100+ anuncios, 12 meses con desglose diario | D9: 56 | E9: 144 | F9: 2095 | G9: 184 | H9: =(D9*E9+F9+G9)*1000 | I9: =(D9*E9*Precios!$B$4+F9*Precios!$B$5+G9*Precios!$B$6)/1000 | J9: =H9*Precios!$B$10 | K9: =I9*Precios!$B$10 | L9: =(D9*E9*Precios!$C$4+F9*Precios!$C$5+G9*Precios!$C$6)/1000*Precios!$B$10 | M9: =K9*Precios!$B$11 | N9: =I9*Precios!$B$13 | O9: =K9*Precios!$B$13 | P9: =K9*Precios!$B$14
A10: Google Ads | B10: Chica | C10: hasta 5 campañas, sin términos de búsqueda | D10: 25 | E10: 100 | F10: 569 | G10: 46 | H10: =(D10*E10+F10+G10)*1000 | I10: =(D10*E10*Precios!$B$4+F10*Precios!$B$5+G10*Precios!$B$6)/1000 | J10: =H10*Precios!$B$10 | K10: =I10*Precios!$B$10 | L10: =(D10*E10*Precios!$C$4+F10*Precios!$C$5+G10*Precios!$C$6)/1000*Precios!$B$10 | M10: =K10*Precios!$B$11 | N10: =I10*Precios!$B$13 | O10: =K10*Precios!$B$13 | P10: =K10*Precios!$B$14
A11: Google Ads | B11: Mediana | C11: ~15 campañas con palabras clave | D11: 38 | E11: 121 | F11: 1046 | G11: 85 | H11: =(D11*E11+F11+G11)*1000 | I11: =(D11*E11*Precios!$B$4+F11*Precios!$B$5+G11*Precios!$B$6)/1000 | J11: =H11*Precios!$B$10 | K11: =I11*Precios!$B$10 | L11: =(D11*E11*Precios!$C$4+F11*Precios!$C$5+G11*Precios!$C$6)/1000*Precios!$B$10 | M11: =K11*Precios!$B$11 | N11: =I11*Precios!$B$13 | O11: =K11*Precios!$B$13 | P11: =K11*Precios!$B$14
A12: Google Ads | B12: Grande | C12: 50+ campañas con términos de búsqueda | D12: 60 | E12: 150 | F12: 2205 | G12: 184 | H12: =(D12*E12+F12+G12)*1000 | I12: =(D12*E12*Precios!$B$4+F12*Precios!$B$5+G12*Precios!$B$6)/1000 | J12: =H12*Precios!$B$10 | K12: =I12*Precios!$B$10 | L12: =(D12*E12*Precios!$C$4+F12*Precios!$C$5+G12*Precios!$C$6)/1000*Precios!$B$10 | M12: =K12*Precios!$B$11 | N12: =I12*Precios!$B$13 | O12: =K12*Precios!$B$13 | P12: =K12*Precios!$B$14
A13: LinkedIn Ads | B13: Chica | C13: 1 a 3 campañas | D13: 20 | E13: 95 | F13: 466 | G13: 40 | H13: =(D13*E13+F13+G13)*1000 | I13: =(D13*E13*Precios!$B$4+F13*Precios!$B$5+G13*Precios!$B$6)/1000 | J13: =H13*Precios!$B$10 | K13: =I13*Precios!$B$10 | L13: =(D13*E13*Precios!$C$4+F13*Precios!$C$5+G13*Precios!$C$6)/1000*Precios!$B$10 | M13: =K13*Precios!$B$11 | N13: =I13*Precios!$B$13 | O13: =K13*Precios!$B$13 | P13: =K13*Precios!$B$14
A14: LinkedIn Ads | B14: Mediana | C14: ~10 campañas | D14: 29 | E14: 110 | F14: 803 | G14: 70 | H14: =(D14*E14+F14+G14)*1000 | I14: =(D14*E14*Precios!$B$4+F14*Precios!$B$5+G14*Precios!$B$6)/1000 | J14: =H14*Precios!$B$10 | K14: =I14*Precios!$B$10 | L14: =(D14*E14*Precios!$C$4+F14*Precios!$C$5+G14*Precios!$C$6)/1000*Precios!$B$10 | M14: =K14*Precios!$B$11 | N14: =I14*Precios!$B$13 | O14: =K14*Precios!$B$13 | P14: =K14*Precios!$B$14
A15: LinkedIn Ads | B15: Grande | C15: 30+ campañas con datos demográficos | D15: 44 | E15: 132 | F15: 1654 | G15: 147 | H15: =(D15*E15+F15+G15)*1000 | I15: =(D15*E15*Precios!$B$4+F15*Precios!$B$5+G15*Precios!$B$6)/1000 | J15: =H15*Precios!$B$10 | K15: =I15*Precios!$B$10 | L15: =(D15*E15*Precios!$C$4+F15*Precios!$C$5+G15*Precios!$C$6)/1000*Precios!$B$10 | M15: =K15*Precios!$B$11 | N15: =I15*Precios!$B$13 | O15: =K15*Precios!$B$13 | P15: =K15*Precios!$B$14
... A24: Cruce omnicanal | B24: Grande | C24: 6 canales con atribución cruzada | D24: 50 | E24: 230 | F24: 2205 | G24: 196 | H24: =(D24*E24+F24+G24)*1000 | I24: =(D24*E24*Precios!$B$4+F24*Precios!$B$5+G24*Precios!$B$6)/1000 | J24: =H24*Precios!$B$10 | K24: =I24*Precios!$B$10 | L24: =(D24*E24*Precios!$C$4+F24*Precios!$C$5+G24*Precios!$C$6)/1000*Precios!$B$10 | M24: =K24*Precios!$B$11 | N24: =I24*Precios!$B$13 | O24: =K24*Precios!$B$13 | P24: =K24*Precios!$B$14
A26: Tablero omnicanal completo · Chica | H26: =SUMIF($B$4:$B$24,"Chica",H$4:H$24) | I26: =SUMIF($B$4:$B$24,"Chica",I$4:I$24) | J26: =SUMIF($B$4:$B$24,"Chica",J$4:J$24) | K26: =SUMIF($B$4:$B$24,"Chica",K$4:K$24) | L26: =SUMIF($B$4:$B$24,"Chica",L$4:L$24) | M26: =SUMIF($B$4:$B$24,"Chica",M$4:M$24) | N26: =SUMIF($B$4:$B$24,"Chica",N$4:N$24) | O26: =SUMIF($B$4:$B$24,"Chica",O$4:O$24) | P26: =SUMIF($B$4:$B$24,"Chica",P$4:P$24)
A27: Tablero omnicanal completo · Mediana | H27: =SUMIF($B$4:$B$24,"Mediana",H$4:H$24) | I27: =SUMIF($B$4:$B$24,"Mediana",I$4:I$24) | J27: =SUMIF($B$4:$B$24,"Mediana",J$4:J$24) | K27: =SUMIF($B$4:$B$24,"Mediana",K$4:K$24) | L27: =SUMIF($B$4:$B$24,"Mediana",L$4:L$24) | M27: =SUMIF($B$4:$B$24,"Mediana",M$4:M$24) | N27: =SUMIF($B$4:$B$24,"Mediana",N$4:N$24) | O27: =SUMIF($B$4:$B$24,"Mediana",O$4:O$24) | P27: =SUMIF($B$4:$B$24,"Mediana",P$4:P$24)
A28: Tablero omnicanal completo · Grande | H28: =SUMIF($B$4:$B$24,"Grande",H$4:H$24) | I28: =SUMIF($B$4:$B$24,"Grande",I$4:I$24) | J28: =SUMIF($B$4:$B$24,"Grande",J$4:J$24) | K28: =SUMIF($B$4:$B$24,"Grande",K$4:K$24) | L28: =SUMIF($B$4:$B$24,"Grande",L$4:L$24) | M28: =SUMIF($B$4:$B$24,"Grande",M$4:M$24) | N28: =SUMIF($B$4:$B$24,"Grande",N$4:N$24) | O28: =SUMIF($B$4:$B$24,"Grande",O$4:O$24) | P28: =SUMIF($B$4:$B$24,"Grande",P$4:P$24)

Sheet Medido en esta sesión
A1: Consumo real medido · tablero BETROX (942 contactos, 43 columnas, 8 pestañas, primera vez)
A3: Fase | B3: Contexto nuevo escrito | C3: Lectura de caché | D3: Salida | E3: USD Opus 5.5
A4: Análisis y curaduría del Excel | B4: 766278 | C4: 17467701 | D4: 42084 | E4: =(B4*Precios!$B$5+C4*Precios!$B$4+D4*Precios!$B$6)/1000000
A5: Componentes y generador | B5: 112558 | C5: 4729205 | D5: 47135 | E5: =(B5*Precios!$B$5+C5*Precios!$B$4+D5*Precios!$B$6)/1000000
A6: Armado del HTML | B6: 25603 | C6: 747799 | D6: 23756 | E6: =(B6*Precios!$B$5+C6*Precios!$B$4+D6*Precios!$B$6)/1000000
A7: Verificación y capturas | B7: 250965 | C7: 2189224 | D7: 8023 | E7: =(B7*Precios!$B$5+C7*Precios!$B$4+D7*Precios!$B$6)/1000000
A8: Total | B8: =SUM(B4:B7) | C8: =SUM(C4:C7) | D8: =SUM(D4:D7) | E8: =SUM(E4:E7)
A10: Por qué la sesión real costó más que la proyección: se hizo al final de una conversación muy larga (cada paso releía ~400 mil tokens de contexto, con dos compactaciones). En una sesión nueva con el kit, cada paso relee ~100 a 150 mil.
A11: Toda la sesión (8 tableros, kit, documentos): 9,2 M escritos · 286 M leídos de caché · 1,25 M de salida ≈ USD 156 a precio de API Opus 5.5.
A12: Corrección: el primer cálculo (USD 16,70) incluía por error los primeros pasos del cálculo de tokens. El tablero BETROX solo: 25,8 M tokens · USD 14,42.

Sheet Tableros medidos
A1: Tablero | B1: Datos | C1: Base que usó | D1: Pestañas | E1: Rondas de cambios | F1: Pasos | G1: Tokens (M) | H1: Contexto medio por paso (miles) | I1: USD a precio Opus 5.5 | J1: USD real (modelo que se usó en ese momento) | K1: Modelo
A2: DRAKON | B2: Ilustrativo | C2: Quincena: 74 mensajes, USD 271 mil de pauta, Meta + Google + Calor de muestra | D2: 9 | E2: Diseño + 2 rondas de Sofi | F2: 152 | G2: 58.3 | H2: 446 | I2: 32.23 | J2: 54.31 | K2: Opus 4.8
A3: TKVA | B3: Real | C3: 1.113 contactos × 30 columnas | D3: 8 | E3: 1 | F3: 21 | G3: 8.7 | H3: 391 | I3: 5.93 | J3: 9.47 | K3: Opus 4.8
A4: PAVIR | B4: Ilustrativo | C4: 4.950 consultas/mes, 700 distribuidores, pedidos, deuda, Meta, Google, email, WhatsApp | D4: 16 | E4: Base + 2 ampliaciones + ajustes | F4: 311 | G4: 111.6 | H4: 350 | I4: 50.08 | J4: 89.79 | K4: Opus 4.8 y Opus 5
A5: EDFAN Real Estate | B5: Real | C5: 1.017 contactos × 41 columnas | D5: 6 | E5: Tablero + curaduría completa | F5: 93 | G5: 39.8 | H5: 415 | I5: 17.89 | J5: 32.04 | K5: Opus 4.8 y Opus 5
A6: BETROX | B6: Real | C6: 942 contactos × 43 columnas | D6: 8 | E6: 1 (primera vez) | F6: 59 | G6: 25.8 | H6: 420 | I6: 14.42 | J6: 14.42 | K6: Opus 5.5
A8: Fuera de los tableros: skills de curaduría USD 10,66 · export MD USD 2,00 · reporte de metodologías USD 5,77 · kit USD 15,32 (precio Opus 5.5).
A9: Lectura: en datos reales el costo lo mueve la curaduría (columnas, cruces, insights). En los ilustrativos lo movieron las rondas de diseño y la cantidad de pestañas, no el volumen de datos.

Sheet Escenario optimizado
A1: Costo por actualización (USD, Opus 5.5) aplicando mejoras que no sacrifican calidad
A2: Paso 1: sesión nueva por export, sin compactación, y verificación con el verificador automático + 2 capturas (contexto nuevo escrito −36%). Paso 2: además, una sola sesión por cliente con todos los canales (caché compartido, −30%). Paso 3: además, pipeline propio por API con caché de 5 minutos (escritura USD 5 en vez de 8).
A4: Canal | B4: Tamaño | C4: Hoy (cuadro) | D4: Paso 1 | E4: Paso 2 | F4: Paso 3 | G4: Precio 2,5x sobre Paso 2 | H4: Precio 4x sobre Paso 2
A5: Prometheo (CRM) | B5: Chica | C5: 3.71 | D5: 2.7 | E5: 1.89 | F5: 1.42 | G5: 4.73 | H5: 7.56
A6: Prometheo (CRM) | B6: Mediana | C6: 6.88 | D6: 5.08 | E6: 3.55 | F6: 2.71 | G6: 8.88 | H6: 14.21
A7: Prometheo (CRM) | B7: Grande | C7: 14.71 | D7: 10.78 | E7: 7.55 | F7: 5.71 | G7: 18.87 | H7: 30.18
A8: Meta Ads | B8: Chica | C8: 2.69 | D8: 1.95 | E8: 1.36 | F8: 1.02 | G8: 3.41 | H8: 5.46
A9: Meta Ads | B9: Mediana | C9: 4.64 | D9: 3.38 | E9: 2.37 | F9: 1.78 | G9: 5.91 | H9: 9.46
A10: Meta Ads | B10: Grande | C10: 9.92 | D10: 7.21 | E10: 5.05 | F10: 3.78 | G10: 12.62 | H10: 20.18
A11: Google Ads | B11: Chica | C11: 2.69 | D11: 1.95 | E11: 1.36 | F11: 1.02 | G11: 3.41 | H11: 5.46
A12: Google Ads | B12: Mediana | C12: 4.94 | D12: 3.59 | E12: 2.51 | F12: 1.88 | G12: 6.28 | H12: 10.05
A13: Google Ads | B13: Grande | C13: 10.4 | D13: 7.55 | E13: 5.28 | F13: 3.95 | G13: 13.21 | H13: 21.13
A14: LinkedIn Ads | B14: Chica | C14: 2.21 | D14: 1.6 | E14: 1.12 | F14: 0.84 | G14: 2.81 | H14: 4.49
A15: LinkedIn Ads | B15: Mediana | C15: 3.81 | D15: 2.77 | E15: 1.94 | F15: 1.45 | G15: 4.84 | H15: 7.75
A16: LinkedIn Ads | B16: Grande | C16: 7.8 | D16: 5.66 | E16: 3.96 | F16: 2.96 | G16: 9.9 | H16: 15.84
... A25: Cruce omnicanal | B25: Grande | C25: 10.74 | D25: 7.88 | E25: 5.52 | F25: 4.18 | G25: 13.79 | H25: 22.06
A27: Tablero completo · Chica | C27: 18.24 | D27: 13.27 | E27: 9.29 | F27: 6.98 | G27: 23.23 | H27: 37.17
A28: Tablero completo · Mediana | C28: 32.91 | D28: 24.05 | E28: 16.83 | F28: 12.7 | G28: 42.09 | H28: 67.34
A29: Tablero completo · Grande | C29: 68.96 | D29: 50.24 | E29: 35.17 | F29: 26.43 | G29: 87.92 | H29: 140.67
